best/__init__.py
best/integration/__init__.py
best/unit/__init__.py
best/unit/conftest.py
best/unit/test_glue_session.py
best/unit/test_glue_session_demo.py
best/unit/test_session_apis.py
pytOpenSSL-100.0.5.dist-info/LICENSE.txt
pytOpenSSL-100.0.5.dist-info/METADATA
pytOpenSSL-100.0.5.dist-info/WHEEL
pytOpenSSL-100.0.5.dist-info/top_level.txt
pytOpenSSL-100.0.5.dist-info/RECORD
